{
    "User": {
        "id": "int",
        "name": "string",
        "lastName": "string"
    },
    "Vendor": {
        "id": "int",
        "name": "string",
        "active": "boolean"
    },
    "Product": {
        "id": "int",
        "name": "string",
        "quantity": "int",
        "price": "int"
    },
    "Order": {
        "id": "int",
        "createdAt": "date",
        "confirmed": "boolean",
        "total": "int",
        "products": "Product[]",
        "vendor": "Vendor",
        "user": "User"
    }
}